mediawikiimporter
