Metadata-Version: 1.0
Name: MediawikiImporter
Version: 0.1.1
Summary: Mediawiki Importer plugin for the Allura platform
Home-page: http://sf.net/p/mediawikiimporter
Author: Igor Bondarenko
Author-email: jetmind2@gmail.com
License: GPLv3
Platform: UNKNOWN
